openfga_mcp/__init__.py
openfga_mcp/__main__.py
openfga_mcp/openfga.py
openfga_mcp/server.py
openfga_mcp/sse.py
openfga_mcp-0.1.2.dist-info/METADATA
openfga_mcp-0.1.2.dist-info/WHEEL
openfga_mcp-0.1.2.dist-info/entry_points.txt
openfga_mcp-0.1.2.dist-info/licenses/LICENSE
openfga_mcp-0.1.2.dist-info/RECORD
