Metadata-Version: 2.4
Name: openfga-mcp
Version: 0.1.2
Summary: Model Context Protocol (MCP) server for OpenFGA
Project-URL: Homepage, https://github.com/evansims/openfga-mcp
Project-URL: Repository, https://github.com/evansims/openfga-mcp
Project-URL: Issues, https://github.com/evansims/openfga-mcp/issues
Author: Evan Sims
Maintainer-email: Evan Sims <hello@evansims.com>
License: Apache-2.0
License-File: LICENSE
Keywords: automation,git,llm,mcp
Classifier: Development Status :: 3 - Alpha
Classifier: Intended Audience :: Developers
Classifier: License :: OSI Approved :: Apache Software License
Classifier: Programming Language :: Python :: 3.12
Requires-Python: >=3.12
Requires-Dist: httpx>=0.27
Requires-Dist: mcp>=1.4
Requires-Dist: openfga-sdk>=0.9
Requires-Dist: starlette>=0.27
Requires-Dist: uvicorn>=0.23
